faster_coco_eval_aitod/__init__.py
faster_coco_eval_aitod/faster_eval_api_cpp.cpython-39-x86_64-linux-gnu.so
faster_coco_eval_aitod/mask_api_new_cpp.cpython-39-x86_64-linux-gnu.so
faster_coco_eval_aitod/version.py
faster_coco_eval_aitod/core/__init__.py
faster_coco_eval_aitod/core/coco.py
faster_coco_eval_aitod/core/cocoeval.py
faster_coco_eval_aitod/core/faster_eval_api.py
faster_coco_eval_aitod/core/mask.py
faster_coco_eval_aitod/extra/__init__.py
faster_coco_eval_aitod/extra/curves.py
faster_coco_eval_aitod/extra/display.py
faster_coco_eval_aitod/extra/draw.py
faster_coco_eval_aitod/extra/extra.py
faster_coco_eval_aitod/extra/utils.py
faster_coco_eval_aitod-1.0.2.data/data/extra.txt
faster_coco_eval_aitod-1.0.2.data/data/runtime.txt
faster_coco_eval_aitod-1.0.2.data/data/tests.txt
faster_coco_eval_aitod-1.0.2.dist-info/LICENSE
faster_coco_eval_aitod-1.0.2.dist-info/METADATA
faster_coco_eval_aitod-1.0.2.dist-info/WHEEL
faster_coco_eval_aitod-1.0.2.dist-info/top_level.txt
faster_coco_eval_aitod-1.0.2.dist-info/RECORD
