Metadata-Version: 2.1
Name: faster-coco-eval-aitod
Version: 1.0.2
Summary: a fork of Faster-COCO-Eval modified specifically for the AI-TOD dataset
Home-page: https://github.com/RicePasteM/faster_coco_eval_aitod
Author: RicePasteM
Author-email: huzhangchi@mail.ustc.edu.cn
License: UNKNOWN
Platform: UNKNOWN
Classifier: Development Status :: 4 - Beta
Classifier: License :: OSI Approved :: Apache Software License
Classifier: Operating System :: OS Independent
Classifier: Programming Language :: Python :: 3
Classifier: Programming Language :: Python :: 3.7
Classifier: Programming Language :: Python :: 3.8
Classifier: Programming Language :: Python :: 3.9
Classifier: Programming Language :: Python :: 3.10
Classifier: Programming Language :: Python :: 3.11
Classifier: Programming Language :: Python :: 3.12
Classifier: Programming Language :: Python :: 3.13
Classifier: Topic :: Scientific/Engineering :: Artificial Intelligence
Requires-Python: >=3.7
Requires-Dist: numpy
Requires-Dist: plotly
Requires-Dist: pandas
Requires-Dist: Pillow
Provides-Extra: extra
Requires-Dist: numpy ; extra == 'extra'
Requires-Dist: plotly ; extra == 'extra'
Requires-Dist: pandas ; extra == 'extra'
Requires-Dist: Pillow ; extra == 'extra'
Requires-Dist: opencv-python-headless ; extra == 'extra'
Provides-Extra: tests
Requires-Dist: numpy ; extra == 'tests'
Requires-Dist: plotly ; extra == 'tests'
Requires-Dist: pandas ; extra == 'tests'
Requires-Dist: Pillow ; extra == 'tests'
Requires-Dist: pycocotools ; extra == 'tests'
Requires-Dist: pytest ; extra == 'tests'
Requires-Dist: pytest-cov ; extra == 'tests'
Requires-Dist: parameterized ; extra == 'tests'
